README.md
setup.py
aoeapi/__init__.py
aoeapi.egg-info/PKG-INFO
aoeapi.egg-info/SOURCES.txt
aoeapi.egg-info/dependency_links.txt
aoeapi.egg-info/requires.txt
aoeapi.egg-info/top_level.txt