Metadata-Version: 1.1
Name: aoeapi
Version: 1.0.0
Summary: Python 3 API for ageofempires.com
Home-page: https://github.com/happyleavesaoc/python-aoe-api/
Author: happyleaves
Author-email: happyleaves.tfr@gmail.com
License: MIT
Platform: UNKNOWN
Classifier: License :: OSI Approved :: MIT License
Classifier: Operating System :: OS Independent
Classifier: Programming Language :: Python :: 3
